{
  "annotations": {
    "list": [
      {
        "builtIn": 1,
        "datasource": "-- Grafana --",
        "enable": true,
        "hide": true,
        "iconColor": "rgba(0, 211, 255, 1)",
        "name": "Annotations & Alerts",
        "type": "dashboard"
      }
    ]
  },
  "editable": true,
  "gnetId": null,
  "graphTooltip": 0,
  "id": 2,
  "links": [],
  "panels": [
    {
      "datasource": null,
      "description": "Current cluster health status (green/yellow/red)",
      "fieldConfig": {
        "defaults": {
          "color": {
            "mode": "thresholds"
          },
          "mappings": [
            {
              "options": {
                "0": {
                  "color": "green",
                  "index": 0,
                  "text": "Green"
                },
                "1": {
                  "color": "yellow",
                  "index": 1,
                  "text": "Yellow"
                },
                "2": {
                  "color": "red",
                  "index": 2,
                  "text": "Red"
                }
              },
              "type": "value"
            }
          ],
          "thresholds": {
            "mode": "absolute",
            "steps": [
              {
                "color": "green",
                "value": null
              },
              {
                "color": "yellow",
                "value": 1
              },
              {
                "color": "red",
                "value": 2
              }
            ]
          },
          "unit": "none"
        },
        "overrides": []
      },
      "gridPos": {
        "h": 6,
        "w": 8,
        "x": 0,
        "y": 0
      },
      "id": 6,
      "options": {
        "colorMode": "value",
        "graphMode": "area",
        "justifyMode": "auto",
        "orientation": "auto",
        "reduceOptions": {
          "calcs": [
            "last"
          ],
          "fields": "",
          "values": false
        },
        "textMode": "auto"
      },
      "pluginVersion": "8.3.4",
      "targets": [
        {
          "expr": "opensearch_cluster_health_status",
          "interval": "",
          "legendFormat": "{{cluster}}",
          "refId": "A"
        }
      ],
      "title": "Cluster Health Status",
      "type": "stat"
    },
    {
      "datasource": null,
      "description": "Number of nodes in the cluster",
      "fieldConfig": {
        "defaults": {
          "color": {
            "mode": "thresholds"
          },
          "thresholds": {
            "mode": "absolute",
            "steps": [
              {
                "color": "green",
                "value": null
              }
            ]
          },
          "unit": "none"
        },
        "overrides": []
      },
      "gridPos": {
        "h": 6,
        "w": 8,
        "x": 8,
        "y": 0
      },
      "id": 7,
      "options": {
        "colorMode": "value",
        "graphMode": "area",
        "justifyMode": "auto",
        "orientation": "auto",
        "reduceOptions": {
          "calcs": [
            "last"
          ],
          "fields": "",
          "values": false
        },
        "textMode": "auto"
      },
      "pluginVersion": "8.3.4",
      "targets": [
        {
          "expr": "opensearch_cluster_health_number_of_nodes",
          "interval": "",
          "legendFormat": "{{cluster}}",
          "refId": "A"
        }
      ],
      "title": "Number of Nodes",
      "type": "stat"
    },
    {
      "datasource": null,
      "description": "Number of shards in the cluster",
      "fieldConfig": {
        "defaults": {
          "color": {
            "mode": "thresholds"
          },
          "thresholds": {
            "mode": "absolute",
            "steps": [
              {
                "color": "green",
                "value": null
              }
            ]
          },
          "unit": "none"
        },
        "overrides": []
      },
      "gridPos": {
        "h": 6,
        "w": 8,
        "x": 16,
        "y": 0
      },
      "id": 8,
      "options": {
        "colorMode": "value",
        "graphMode": "area",
        "justifyMode": "auto",
        "orientation": "auto",
        "reduceOptions": {
          "calcs": [
            "last"
          ],
          "fields": "",
          "values": false
        },
        "textMode": "auto"
      },
      "pluginVersion": "8.3.4",
      "targets": [
        {
          "expr": "opensearch_cluster_health_active_shards",
          "interval": "",
          "legendFormat": "Active",
          "refId": "A"
        },
        {
          "expr": "opensearch_cluster_health_initializing_shards",
          "interval": "",
          "legendFormat": "Initializing",
          "refId": "B"
        },
        {
          "expr": "opensearch_cluster_health_relocating_shards",
          "interval": "",
          "legendFormat": "Relocating",
          "refId": "C"
        },
        {
          "expr": "opensearch_cluster_health_unassigned_shards",
          "interval": "",
          "legendFormat": "Unassigned",
          "refId": "D"
        }
      ],
      "title": "Shards",
      "type": "stat"
    },
    {
      "datasource": null,
      "description": "JVM Heap Memory Usage",
      "fieldConfig": {
        "defaults": {
          "color": {
            "mode": "palette-classic"
          },
          "thresholds": {
            "mode": "absolute",
            "steps": [
              {
                "color": "green",
                "value": null
              },
              {
                "color": "red",
                "value": 80
              }
            ]
          },
          "unit": "percent"
        },
        "overrides": []
      },
      "gridPos": {
        "h": 8,
        "w": 12,
        "x": 0,
        "y": 6
      },
      "id": 9,
      "options": {
        "legend": {
          "calcs": [],
          "displayMode": "list",
          "placement": "bottom"
        },
        "tooltip": {
          "mode": "multi",
          "sort": "desc"
        }
      },
      "pluginVersion": "8.3.4",
      "targets": [
        {
          "expr": "(opensearch_jvm_memory_used_bytes{area=\"heap\"} / opensearch_jvm_memory_max_bytes{area=\"heap\"}) * 100",
          "interval": "",
          "legendFormat": "{{node}} (Used)",
          "refId": "A"
        }
      ],
      "title": "JVM Heap Memory Usage",
      "type": "timeseries"
    },
    {
      "datasource": null,
      "description": "Indexing and Search Rates",
      "fieldConfig": {
        "defaults": {
          "color": {
            "mode": "palette-classic"
          },
          "thresholds": {
            "mode": "absolute",
            "steps": [
              {
                "color": "green",
                "value": null
              }
            ]
          },
          "unit": "ops"
        },
        "overrides": []
      },
      "gridPos": {
        "h": 8,
        "w": 12,
        "x": 12,
        "y": 6
      },
      "id": 10,
      "options": {
        "legend": {
          "calcs": [],
          "displayMode": "list",
          "placement": "bottom"
        },
        "tooltip": {
          "mode": "multi",
          "sort": "desc"
        }
      },
      "pluginVersion": "8.3.4",
      "targets": [
        {
          "expr": "rate(opensearch_indices_indexing_index_total[1m])",
          "interval": "",
          "legendFormat": "Indexing Rate ({{index}})",
          "refId": "A"
        },
        {
          "expr": "rate(opensearch_indices_search_query_total[1m])",
          "interval": "",
          "legendFormat": "Search Rate ({{index}})",
          "refId": "B"
        }
      ],
      "title": "Indexing and Search Rates",
      "type": "timeseries"
    }
  ],
  "refresh": "10s",
  "schemaVersion": 33,
  "style": "dark",
  "tags": [],
  "templating": {
    "list": []
  },
  "time": {
    "from": "now-6h",
    "to": "now"
  },
  "timepicker": {
    "refresh_intervals": [
      "5s",
      "10s",
      "30s",
      "1m",
      "5m",
      "15m",
      "30m",
      "1h",
      "2h",
      "1d"
    ]
  },
  "timezone": "",
  "title": "OpenSearch",
  "uid": "opensearch",
  "version": 1
}
